main.py
core/__init__.py
core/ai_assistant.py
core/chat_manager.py
core/permission_manager.py
handlers/__init__.py
handlers/request_handlers.py
utils/image_analyzer.py
utils/mcp_server.py
utils/session_manager.py
utils/streaming_analyzer.py
g_aicoder-1.0.6.dist-info/METADATA
g_aicoder-1.0.6.dist-info/WHEEL
g_aicoder-1.0.6.dist-info/entry_points.txt
g_aicoder-1.0.6.dist-info/top_level.txt
g_aicoder-1.0.6.dist-info/RECORD
