Metadata-Version: 2.4
Name: g-aicoder
Version: 1.0.6
Summary: G-AiCoder - Advanced AI development assistant with multi-modal intelligence
Home-page: https://github.com/prdpspkt/gCoder
Author: gCoder Project
Author-email: G-AiCoder Project <contact@example.com>
License: MIT
Project-URL: Homepage, https://github.com/prdpspkt/gCoder
Project-URL: Repository, https://github.com/prdpspkt/gCoder
Project-URL: Issues, https://github.com/prdpspkt/gCoder/issues
Keywords: ai,assistant,coding,development,claude,ollama,terminal
Classifier: Development Status :: 5 - Production/Stable
Classifier: Intended Audience :: Developers
Classifier: License :: OSI Approved :: MIT License
Classifier: Operating System :: OS Independent
Classifier: Programming Language :: Python :: 3
Classifier: Programming Language :: Python :: 3.8
Classifier: Programming Language :: Python :: 3.9
Classifier: Programming Language :: Python :: 3.10
Classifier: Programming Language :: Python :: 3.11
Classifier: Programming Language :: Python :: 3.12
Classifier: Topic :: Software Development :: Libraries :: Python Modules
Classifier: Topic :: Scientific/Engineering :: Artificial Intelligence
Requires-Python: >=3.8
Requires-Dist: aiohttp>=3.13.0
Requires-Dist: Pillow>=10.0.0
Dynamic: author
Dynamic: home-page
Dynamic: requires-python
